{
    "type": "FeatureCollection",
    "features": [
        {
            "type": "Feature",
            "properties": {},
            "geometry": {
                "coordinates": [
                    [
                        119.32858454732735,
                        34.6904405039847
                    ],
                    [
                        119.34882590052797,
                        34.71352305534859
                    ],
                    [
                        119.4105293804484,
                        34.687219170938434
                    ],
                    [
                        119.42326184455806,
                        34.65902716026062
                    ],
                    [
                        119.38637034598253,
                        34.63942134663826
                    ],
                    [
                        119.37363788187048,
                        34.682386936332676
                    ],
                    [
                        119.34099053799747,
                        34.68748762014698
                    ],
                    [
                        119.34523469270226,
                        34.688292962548786
                    ],
                    [
                        119.34523469270226,
                        34.69473541971014
                    ]
                ],
                "type": "LineString"
            }
        }
    ]
}